nxontology/__init__.py
nxontology/examples.py
nxontology/exceptions.py
nxontology/imports.py
nxontology/node.py
nxontology/ontology.py
nxontology/py.typed
nxontology/similarity.py
nxontology/utils.py
nxontology/viz.py
nxontology/tests/__init__.py
nxontology/tests/conftest.py
nxontology/tests/imports_test.py
nxontology/tests/node_test.py
nxontology/tests/ontology_test.py
nxontology/tests/similarity_test.py
nxontology/tests/similarity_test_disconnected.tsv
nxontology/tests/similarity_test_metal.tsv
nxontology/tests/viz_test.py
nxontology-0.5.0.dist-info/LICENSE
nxontology-0.5.0.dist-info/METADATA
nxontology-0.5.0.dist-info/WHEEL
nxontology-0.5.0.dist-info/top_level.txt
nxontology-0.5.0.dist-info/RECORD
