Metadata-Version: 2.1
Name: nxontology
Version: 0.5.0
Summary: NetworkX for ontologies
Maintainer-email: Daniel Himmelstein <dhimmel@related.vc>
License: Apache
Project-URL: Homepage, https://github.com/related-sciences/nxontology
Keywords: networkx,ontologies,similarity,graphs,networks,digraph,information-content,semantic-similarity
Classifier: License :: OSI Approved :: Apache Software License
Classifier: Operating System :: OS Independent
Classifier: Programming Language :: Python
Classifier: Programming Language :: Python :: 3
Classifier: Topic :: Scientific/Engineering :: Bio-Informatics
Classifier: Topic :: Scientific/Engineering :: Information Analysis
Requires-Python: >=3.8
Provides-Extra: dev
Provides-Extra: viz
License-File: LICENSE
